{
  "legislative_session": "2025-2026",
  "identifier": "HB 2483",
  "title": "Creating a data broker registry.",
  "from_organization": "~{\"classification\": \"lower\"}",
  "classification": [
    "bill"
  ],
  "subject": [],
  "abstracts": [],
  "other_titles": [],
  "other_identifiers": [
    {
      "identifier": "ocd-bill-wa-2025_2026-hb2483"
    }
  ],
  "actions": [
    {
      "description": "First reading, referred to Consumer Protection & Business.",
      "date": "2026-01-14",
      "organization_id": "~{\"classification\": \"lower\"}",
      "classification": [
        "reading-1"
      ],
      "related_entities": [],
      "_processing": {
        "log_file_created": "2026-07-13T06:07:54Z"
      }
    },
    {
      "description": "Public hearing in the House Committee on Consumer Protection & Business at 1:30 PM.",
      "date": "2026-01-20",
      "organization_id": "~{\"classification\": \"lower\"}",
      "classification": [],
      "related_entities": [],
      "_processing": {
        "log_file_created": "2026-07-13T06:07:54Z"
      }
    },
    {
      "description": "Executive session scheduled, but no action was taken in the House Committee on Consumer Protection & Business at 1:30 PM.",
      "date": "2026-02-03",
      "organization_id": "~{\"classification\": \"lower\"}",
      "classification": [],
      "related_entities": [],
      "_processing": {
        "log_file_created": "2026-07-13T06:07:54Z"
      }
    },
    {
      "description": "Executive action taken in the House Committee on Consumer Protection & Business at 1:30 PM.",
      "date": "2026-02-04",
      "organization_id": "~{\"classification\": \"lower\"}",
      "classification": [],
      "related_entities": [],
      "_processing": {
        "log_file_created": "2026-07-13T06:07:54Z"
      }
    },
    {
      "description": "CPB - Majority; 1st substitute bill be substituted, do pass.",
      "date": "2026-02-04",
      "organization_id": "~{\"classification\": \"lower\"}",
      "classification": [
        "substitution"
      ],
      "related_entities": [],
      "_processing": {
        "log_file_created": "2026-07-13T06:07:54Z"
      }
    },
    {
      "description": "Minority; do not pass.",
      "date": "2026-02-04",
      "organization_id": "~{\"classification\": \"lower\"}",
      "classification": [
        "committee-passage-unfavorable"
      ],
      "related_entities": [],
      "_processing": {
        "log_file_created": "2026-07-13T06:07:54Z"
      }
    },
    {
      "description": "Minority; without recommendation.",
      "date": "2026-02-04",
      "organization_id": "~{\"classification\": \"lower\"}",
      "classification": [
        "committee-passage-unfavorable"
      ],
      "related_entities": [],
      "_processing": {
        "log_file_created": "2026-07-13T06:07:54Z"
      }
    },
    {
      "description": "Referred to Appropriations.",
      "date": "2026-02-04",
      "organization_id": "~{\"classification\": \"lower\"}",
      "classification": [
        "referral-committee"
      ],
      "related_entities": [],
      "_processing": {
        "log_file_created": "2026-07-13T06:07:54Z"
      }
    },
    {
      "description": "Public hearing in the House Committee on Appropriations at 10:30 AM.",
      "date": "2026-02-06",
      "organization_id": "~{\"classification\": \"lower\"}",
      "classification": [],
      "related_entities": [],
      "_processing": {
        "log_file_created": "2026-07-13T06:07:54Z"
      }
    }
  ],
  "sponsorships": [
    {
      "name": "Kloba",
      "classification": "primary",
      "entity_type": "person",
      "primary": true,
      "person_id": "~{\"name\": \"Kloba\"}",
      "organization_id": null
    },
    {
      "name": "Donaghy",
      "classification": "cosponsor",
      "entity_type": "person",
      "primary": false,
      "person_id": "~{\"name\": \"Donaghy\"}",
      "organization_id": null
    },
    {
      "name": "Fosse",
      "classification": "cosponsor",
      "entity_type": "person",
      "primary": false,
      "person_id": "~{\"name\": \"Fosse\"}",
      "organization_id": null
    },
    {
      "name": "Ryu",
      "classification": "cosponsor",
      "entity_type": "person",
      "primary": false,
      "person_id": "~{\"name\": \"Ryu\"}",
      "organization_id": null
    },
    {
      "name": "Zahn",
      "classification": "cosponsor",
      "entity_type": "person",
      "primary": false,
      "person_id": "~{\"name\": \"Zahn\"}",
      "organization_id": null
    },
    {
      "name": "Parshley",
      "classification": "cosponsor",
      "entity_type": "person",
      "primary": false,
      "person_id": "~{\"name\": \"Parshley\"}",
      "organization_id": null
    },
    {
      "name": "Farivar",
      "classification": "cosponsor",
      "entity_type": "person",
      "primary": false,
      "person_id": "~{\"name\": \"Farivar\"}",
      "organization_id": null
    },
    {
      "name": "Ramel",
      "classification": "cosponsor",
      "entity_type": "person",
      "primary": false,
      "person_id": "~{\"name\": \"Ramel\"}",
      "organization_id": null
    },
    {
      "name": "Gregerson",
      "classification": "cosponsor",
      "entity_type": "person",
      "primary": false,
      "person_id": "~{\"name\": \"Gregerson\"}",
      "organization_id": null
    },
    {
      "name": "Bronoske",
      "classification": "cosponsor",
      "entity_type": "person",
      "primary": false,
      "person_id": "~{\"name\": \"Bronoske\"}",
      "organization_id": null
    },
    {
      "name": "Cortes",
      "classification": "cosponsor",
      "entity_type": "person",
      "primary": false,
      "person_id": "~{\"name\": \"Cortes\"}",
      "organization_id": null
    },
    {
      "name": "Obras",
      "classification": "cosponsor",
      "entity_type": "person",
      "primary": false,
      "person_id": "~{\"name\": \"Obras\"}",
      "organization_id": null
    },
    {
      "name": "Pollet",
      "classification": "cosponsor",
      "entity_type": "person",
      "primary": false,
      "person_id": "~{\"name\": \"Pollet\"}",
      "organization_id": null
    },
    {
      "name": "Macri",
      "classification": "cosponsor",
      "entity_type": "person",
      "primary": false,
      "person_id": "~{\"name\": \"Macri\"}",
      "organization_id": null
    },
    {
      "name": "Nance",
      "classification": "cosponsor",
      "entity_type": "person",
      "primary": false,
      "person_id": "~{\"name\": \"Nance\"}",
      "organization_id": null
    },
    {
      "name": "Thomas",
      "classification": "cosponsor",
      "entity_type": "person",
      "primary": false,
      "person_id": "~{\"name\": \"Thomas\"}",
      "organization_id": null
    },
    {
      "name": "Callan",
      "classification": "cosponsor",
      "entity_type": "person",
      "primary": false,
      "person_id": "~{\"name\": \"Callan\"}",
      "organization_id": null
    }
  ],
  "related_bills": [],
  "versions": [],
  "documents": [],
  "citations": [
    {
      "publication": "Revised Code of Washington",
      "citation": "18.235.020",
      "citation_type": "proposed",
      "effective": null,
      "expires": null,
      "url": "https://app.leg.wa.gov/RCW/default.aspx?cite=18.235.020"
    },
    {
      "publication": "Revised Code of Washington",
      "citation": "19",
      "citation_type": "proposed",
      "effective": null,
      "expires": null,
      "url": "https://app.leg.wa.gov/RCW/default.aspx?cite=19"
    }
  ],
  "sources": [
    {
      "url": "https://app.leg.wa.gov/billsummary/?BillNumber=2483&Year=2025&Initiative=false",
      "note": ""
    }
  ],
  "extras": {},
  "jurisdiction": {
    "id": "ocd-jurisdiction/country:us/state:wa/government",
    "name": "Washington",
    "classification": "state",
    "division_id": "ocd-division/country:us/state:wa"
  },
  "_processing": {
    "logs_latest_update": "2026-07-13T06:07:54Z",
    "text_extraction_latest_update": "2026-07-14T20:24:34.413315Z"
  }
}